{
	"data": [
		{
			"id": "1",
			"code": "f230fh0g3",
			"name": "Asylum Demon",
			"image": "asylum.jpg",
			"city": "Northern Undead Asylum",
			"category": "1",
			"quantity": 24,
			"inventoryStatus": "facil",
			"rating": 5,
			"runes": "",
			"lore": "Antes defensores honrados de Shurima contra o temido Vazio, Aatrox e sua raça no fim se tornaram uma ameaça ainda maior para Runeterra e a única coisa capaz de derrotá-los foi um tipo de feitiçaria mortal e traiçoeira. Mas após séculos de encarceramento, Aatrox foi o primeiro a encontrar a liberdade novamente, corrompendo e transformando qualquer tolo que tentasse empunhar a arma mágica que continha sua essência. Agora, com um corpo roubado, ele vaga por Runeterra transfigurado, em uma versão bizarra da sua forma anterior, buscando uma vingança apocalíptica."
		},
		{
			"id": "2",
			"code": "nvklal433",
			"name": "Taurus Demon",
			"image": "taurus.jpg",
			"city": "Undead Burg",
			"category": "2",
			"quantity": 61,
			"inventoryStatus": "facil",
			"rating": 4,
			"runes": "",
			"lore": ""
		},
		{
			"id": "3",
			"code": "zz21cz3c1",
			"name": "Bell Gargoyles",
			"image": "gargoyle.jpg",
			"city": "Undead Parish",
			"category": "3",
			"quantity": 2,
			"inventoryStatus": "facil",
			"rating": 3,
			"runes": "",
			"lore": ""
		},
		{
			"id": "4",
			"code": "244wgerg2",
			"name": "Moonlight Butterfly",
			"image": "moonlight-butterfly.jpg",
			"city": "Darkroot Garden",
			"category": "4",
			"quantity": 25,
			"inventoryStatus": "dificil",
			"rating": 5,
			"runes": "",
			"lore": ""
		},
		{
			"id": "5",
			"code": "h456wer53",
			"name": "Capra Demon",
			"image": "capra-demon.jpg",
			"city": "Lower Undead Burg",
			"category": "5",
			"quantity": 73,
			"inventoryStatus": "moderado",
			"rating": 4,
			"runes": "",
			"lore": ""
		},
		{
			"id": "6",
			"code": "av2231fwg",
			"name": "Gaping Dragon",
			"image": "gaping-dragon.jpg",
			"city": "The Depths",
			"category": "6",
			"quantity": 0,
			"inventoryStatus": "facil",
			"rating": 4,
			"runes": "",
			"lore": ""
		},
		{
			"id": "7",
			"code": "bib36pfvm",
			"name": "Stray Demon",
			"image": "stray-demon.jpg",
			"city": "Undead Asylum",
			"category": "7",
			"quantity": 5,
			"inventoryStatus": "dificil",
			"rating": 3,
			"runes": "",
			"lore": ""
		},
		{
			"id": "8",
			"code": "mbvjkgip5",
			"name": "Chaos Witch Quelaag",
			"image": "chaos-witch-quelaag.jpg",
			"city": "Blighttown",
			"category": "8",
			"quantity": 23,
			"inventoryStatus": "moderado",
			"rating": 5,
			"runes": "",
			"lore": ""
		},
		{
			"id": "9",
			"code": "vbb124btr",
			"name": "Great Grey Wolf Sif",
			"image": "sif.jpg",
			"city": "Darkroot Garden",
			"category": "9",
			"quantity": 2,
			"inventoryStatus": "dificil",
			"rating": 4,
			"runes": "",
			"lore": "Emergindo da sombra do luar com suas armas em mãos, Aphelios abate os inimigos de sua fé em absoluto silêncio, comunicando-se apenas pela destreza de sua mira e o disparo de cada arma. Embora viva sob o efeito de um veneno que o emudeceu, ele é guiado por sua irmã Alune, que habita um santuário distante de onde invoca um arsenal de armas de pedra da lua para ajudá-lo. Enquanto a Lua brilhar no céu, Aphelios nunca estará sozinho."
		},
		{
			"id": "10",
			"code": "cm230f032",
			"name": "Iron Golem",
			"image": "iIron-golem.jpg",
			"city": "Sen’s Fortress",
			"category": "10",
			"quantity": 63,
			"inventoryStatus": "moderado",
			"rating": 3,
			"runes": "",
			"lore": ""
		},
		{
			"id": "11",
			"code": "plb34234v",
			"name": "Crossbreed Priscilla",
			"image": "priscilla.jpg",
			"city": "Painted World of Ariamis",
			"category": "11",
			"quantity": 0,
			"inventoryStatus": "moderado",
			"rating": 4,
			"runes": "",
			"lore": ""
		},
		{
			"id": "12",
			"code": "4920nnc2d",
			"name": "Ornstein and Smough",
			"image": "ornstein.jpg",
			"city": "Anor Londo",
			"category": "12",
			"quantity": 23,
			"inventoryStatus": "dificil",
			"rating": 4,
			"runes": "",
			"lore": ""
		},
		{
			"id": "13",
			"code": "250vm23cc",
			"name": "Dark Sun Gwyndolin",
			"image": "gwyndolin.jpg",
			"city": "Kiln of the First Flame",
			"category": "13",
			"quantity": 74,
			"inventoryStatus": "dificil",
			"rating": 5,
			"runes": "",
			"lore": ""
		},
		{
			"id": "14",
			"code": "fldsmn31b",
			"name": "Pinwheel",
			"image": "pinwheel.jpg",
			"city": "The Catacombs",
			"category": "14",
			"quantity": 0,
			"inventoryStatus": "moderado",
			"rating": 3,
			"runes": "",
			"lore": ""
		},
		{
			"id": "15",
			"code": "waas1x2as",
			"name": "Gravelord Nito",
			"description": "a Vingança Flamejante",
			"image": "gravelord-nito.jpg",
			"city": "Tomb of the Giants",
			"category": "15",
			"quantity": 8,
			"inventoryStatus": "moderado",
			"rating": 5,
			"runes": "",
			"lore": ""
		},
		{
			"id": "16",
			"code": "vb34btbg5",
			"name": "Seath the Scaleless",
			"image": "seath-the-scaleless.jpg",
			"city": "Crystal Cave",
			"category": "16",
			"quantity": 34,
			"inventoryStatus": "facil",
			"rating": 4,
			"runes": "",
			"lore": ""
		},
		{
			"id": "17",
			"code": "k8l6j58jl",
			"name": "The Four Kings",
			"image": "four-kings.jpg",
			"city": "New Londo Ruins",
			"category": "17",
			"quantity": 12,
			"inventoryStatus": "moderado",
			"rating": 3,
			"runes": "",
			"lore": ""
		},
		{
			"id": "18",
			"code": "v435nn85n",
			"name": "Ceaseless Discharge",
			"image": "ceaseless.jpg",
			"city": "Demon Ruins",
			"category": "18",
			"quantity": 42,
			"inventoryStatus": "moderado",
			"rating": 4,
			"runes": "",
			"lore": ""
		},
		{
			"id": "19",
			"code": "09zx9c0zc",
			"name": "Centipede Demon",
			"image": "centipede.jpg",
			"city": "Demon Ruins",
			"category": "19",
			"quantity": 41,
			"inventoryStatus": "dificil",
			"rating": 5,
			"runes": "",
			"lore": ""
		},
		{
			"id": "20",
			"code": "mnb5mb2m5",
			"name": "Firesage Demon",
			"image": "firesagehogath.jpg",
			"city": "Demon Ruins",
			"category": "20",
			"quantity": 63,
			"inventoryStatus": "moderado",
			"rating": 4,
			"runes": "",
			"lore": ""
		},
		{
			"id": "21",
			"code": "mnb5mb2m5",
			"name": "Bed of Chaos",
			"image": "bed-of-chaos.jpg",
			"city": "Lost Izazlith",
			"category": "21",
			"quantity": 63,
			"inventoryStatus": "moderado",
			"rating": 4,
			"runes": "",
			"lore": ""
		},
		{
			"id": "22",
			"code": "mnb5mb2m5",
			"name": "Gwyn, Lord of Cinder",
			"image": "gwyn.jpg",
			"city": "Kiln of the First Flame",
			"category": "22",
			"quantity": 63,
			"inventoryStatus": "moderado",
			"rating": 4,
			"runes": "",
			"lore": ""
		},
		{
			"id": "23",
			"code": "mnb5mb2m5",
			"name": "Sanctuary Guardian",
			"image": "sactuary-guard.bmp",
			"city": "Sanctuary Garden",
			"category": "23",
			"quantity": 63,
			"inventoryStatus": "moderado",
			"rating": 4,
			"runes": "",
			"lore": ""
		},
		{
			"id": "24",
			"code": "mnb5mb2m5",
			"name": "Artorias the Abysswalker",
			"image": "artorias.jpg",
			"city": "Royal Wood",
			"category": "24",
			"quantity": 63,
			"inventoryStatus": "moderado",
			"rating": 4,
			"runes": "",
			"lore": ""
		},
		{
			"id": "25",
			"code": "mnb5mb2m5",
			"name": "Black Dragon Kalameet'",
			"image": "black-dragon.jpg",
			"city": "Royal Wood",
			"category": "25",
			"quantity": 63,
			"inventoryStatus": "moderado",
			"rating": 4,
			"runes": "",
			"lore": ""
		},
		{
			"id": "26",
			"code": "mnb5mb2m5",
			"name": "Manus, Father of the Abyss",
			"image": "manus.jpg",
			"city": "Chasm of the Abyss",
			"category": "26",
			"quantity": 63,
			"inventoryStatus": "moderado",
			"rating": 4,
			"runes": "",
			"lore": ""
		}
	]
}